yapystun/__init__.py
yapystun/cli.py
yapystun-0.2.2.dist-info/LICENSE
yapystun-0.2.2.dist-info/METADATA
yapystun-0.2.2.dist-info/WHEEL
yapystun-0.2.2.dist-info/entry_points.txt
yapystun-0.2.2.dist-info/RECORD
